extratools/__init__.py
extratools/datastructures.py
extratools/numbertools.py
extratools/stringtools.py
extra_tools-1.1.5.dist-info/LICENSE
extra_tools-1.1.5.dist-info/METADATA
extra_tools-1.1.5.dist-info/WHEEL
extra_tools-1.1.5.dist-info/top_level.txt
extra_tools-1.1.5.dist-info/RECORD
